ocetrac/__init__.py
ocetrac/_ocetrac_version.py
ocetrac/_version.py
ocetrac/tracker.py
ocetrac/measures/__init__.py
ocetrac/measures/intensity_measures.py
ocetrac/measures/motion_measures.py
ocetrac/measures/plotting.py
ocetrac/measures/shape_measures.py
ocetrac/measures/temporal_measures.py
ocetrac/measures/utils.py
ocetrac/utils/__init__.py
ocetrac/utils/cesm2_lens_utils.py
ocetrac/utils/cesm_anomalies.py
ocetrac-0.1.6.dist-info/LICENSE.txt
ocetrac-0.1.6.dist-info/METADATA
ocetrac-0.1.6.dist-info/WHEEL
ocetrac-0.1.6.dist-info/top_level.txt
ocetrac-0.1.6.dist-info/RECORD
