Metadata-Version: 2.1
Name: ocetrac
Version: 0.1.6
Summary: Label and track unique geospatial features from gridded datasets
Home-page: https://github.com/ocetrac/ocetrac
Author: ocetrac
Author-email: scannell@ldeo.columbia.edu
License: MIT
Classifier: Development Status :: 5 - Production/Stable
Classifier: Topic :: Scientific/Engineering
Classifier: Intended Audience :: Science/Research
Classifier: Operating System :: OS Independent
Classifier: Programming Language :: Python
Classifier: Programming Language :: Python :: 3
Classifier: Programming Language :: Python :: 3.6
Classifier: Programming Language :: Python :: 3.7
Classifier: Programming Language :: Python :: 3.8
Classifier: License :: OSI Approved :: MIT License
Requires-Python: >=3.6
License-File: LICENSE.txt
Requires-Dist: numpy
Requires-Dist: requests
Requires-Dist: xarray
Requires-Dist: dask
Requires-Dist: scipy
Requires-Dist: scikit-image
